itla/__init__.py
itla/itla.py
itla/itla12.py
itla/itla13.py
itla/itla_errors.py
itla/pplaser.py
itla/utils.py
itla/registers/registers_itla.yaml
itla/registers/registers_itla12.yaml
itla/registers/registers_pp.yaml
pytla-0.1.0.dist-info/LICENSE.md
pytla-0.1.0.dist-info/METADATA
pytla-0.1.0.dist-info/WHEEL
pytla-0.1.0.dist-info/top_level.txt
pytla-0.1.0.dist-info/RECORD
