Metadata-Version: 2.1
Name: pytla
Version: 0.1.0
Summary: A python library for controlling ITLA and microITLA devices.
Home-page: https://github.com/alexrkaufman/pytla
Author: Alex Kaufman
Author-email: alexanderkaufman@montana.edu
License: UNKNOWN
Project-URL: Bug Tracker, https://github.com/alexrkaufman/pytla/issues
Project-URL: Docs, https://alexrkaufman.github.io/pytla/
Platform: UNKNOWN
Classifier: Programming Language :: Python :: 3
Classifier: License :: OSI Approved :: MIT License
Classifier: Operating System :: OS Independent
Requires-Python: >=3.6
License-File: LICENSE.md
Requires-Dist: pyserial
Requires-Dist: pyyaml
Requires-Dist: scipy
